migrations/0001_initial.py
migrations/0002_alter_links_options_links_sticky.py
migrations/0003_links_url_hashed_alter_links_id.py
migrations/0004_alter_links_url_hashed.py
migrations/0005_alter_links_date_created.py
migrations/0006_alter_links_date_created.py
migrations/0007_alter_links_tags.py
migrations/__init__.py
shaarpy/__init__.py
shaarpy/admin.py
shaarpy/apps.py
shaarpy/asgi.py
shaarpy/env.sample
shaarpy/forms.py
shaarpy/models.py
shaarpy/settings.py
shaarpy/tools.py
shaarpy/urls.py
shaarpy/wsgi.py
shaarpy/management/commands/export_md.py
shaarpy/management/commands/import.py
shaarpy/management/commands/import_pelican.py
shaarpy/management/commands/import_pelican_folder.py
shaarpy/migrations/0001_initial.py
shaarpy/migrations/0002_alter_links_options_links_sticky.py
shaarpy/migrations/0003_links_url_hashed_alter_links_id.py
shaarpy/migrations/0004_alter_links_url_hashed.py
shaarpy/migrations/0005_alter_links_date_created.py
shaarpy/migrations/0006_alter_links_date_created.py
shaarpy/migrations/0007_alter_links_tags.py
shaarpy/migrations/__init__.py
shaarpy/static/shaarpy.png
shaarpy/templates/base.html
shaarpy/templates/edit_me.html
shaarpy/templates/me.html
shaarpy/templates/registration/login.html
shaarpy/templates/shaarpy/403.html
shaarpy/templates/shaarpy/404.html
shaarpy/templates/shaarpy/500.html
shaarpy/templates/shaarpy/daily_list.html
shaarpy/templates/shaarpy/links_confirm_delete.html
shaarpy/templates/shaarpy/links_detail.html
shaarpy/templates/shaarpy/links_form.html
shaarpy/templates/shaarpy/links_list.html
shaarpy/templates/shaarpy/search.html
shaarpy/templates/shaarpy/tags_list.html
shaarpy/templatetags/__init__.py
shaarpy/templatetags/shaarpy_extras.py
shaarpy/tests/__init__.py
shaarpy/tests/brunus-wgamesolv-framagit.md
shaarpy/tests/hacker-news-avec-django.md
shaarpy/tests/test_commands.py
shaarpy/tests/test_common.py
shaarpy/tests/test_conf.py
shaarpy/tests/test_models.py
shaarpy/tests/test_templatetags.py
shaarpy/tests/test_version.py
shaarpy-1.2.0.dist-info/LICENSE
shaarpy-1.2.0.dist-info/METADATA
shaarpy-1.2.0.dist-info/WHEEL
shaarpy-1.2.0.dist-info/top_level.txt
shaarpy-1.2.0.dist-info/RECORD
