Metadata-Version: 2.1
Name: shaarpy
Version: 1.2.0
Summary: ShaarPy: Share your thoughts, links, ideas, notes. self-hosting bookmarks and micro blogging. If you ever wanted Shaarli in python, that's it ^_*
Home-page: https://github.com/foxmask/shaarpy/
Author: 폭스마스크
Author-email: 폭스마스크 <foxmask+git@pm.me>
License: DO WHAT THE FUCK YOU WANT TO PUBLIC LICENSE
Project-URL: Homepage, https://github.com/foxmask/shaarpy/
Project-URL: Documentation, https://github.com/foxmask/shaarpy/blob/main/README.md
Project-URL: Source, https://github.com/foxmask/shaarpy/
Keywords: python django shaarli
Classifier: Development Status :: 4 - Beta
Classifier: Environment :: Web Environment
Classifier: Intended Audience :: Developers
Classifier: License :: Public Domain
Classifier: Operating System :: OS Independent
Classifier: Programming Language :: Python :: 3.11
Classifier: Programming Language :: Python :: 3.12
Classifier: Topic :: Internet
Classifier: Topic :: Communications
Classifier: Topic :: Database
Requires-Python: >=3.11
License-File: LICENSE
Requires-Dist: Django==5.1.2
Requires-Dist: Jinja2==3.1.4
Requires-Dist: Markdown==3.7
Requires-Dist: Pygments==2.18.0
Requires-Dist: django-environ==0.11.2
Requires-Dist: django-simple-search==1.0.2
Requires-Dist: python-slugify==8.0.4
Requires-Dist: pytz==2024.2
Requires-Dist: rich==13.9.4
Provides-Extra: lint
Requires-Dist: ruff==0.7.3; extra == "lint"
Provides-Extra: test
Requires-Dist: bandit; extra == "test"
Requires-Dist: build; extra == "test"
Requires-Dist: coverage; extra == "test"
Requires-Dist: django-debug-toolbar; extra == "test"
Requires-Dist: pip-audit; extra == "test"
Requires-Dist: pipdeptree; extra == "test"
Requires-Dist: pytest-django; extra == "test"
Requires-Dist: twine; extra == "test"
Requires-Dist: wheel; extra == "test"
